mca/__init__.py
mca/__main__.py
mca/bin2json.py
mca/forge.py
mca/identifiers.py
mca/mca.py
mca/probe.py
mca/probing.py
mca/record.py
mca/topology.py
mca_traceroute-1.0.0.dist-info/LICENSE
mca_traceroute-1.0.0.dist-info/METADATA
mca_traceroute-1.0.0.dist-info/WHEEL
mca_traceroute-1.0.0.dist-info/entry_points.txt
mca_traceroute-1.0.0.dist-info/top_level.txt
mca_traceroute-1.0.0.dist-info/RECORD
