Metadata-Version: 2.1
Name: mca-traceroute
Version: 1.0.0
Summary: mca-traceroute: Detection and Classification of Load Balancers
Home-page: https://www.dcc.ufmg.br/~rlca/mca
Author: Rafael Almeida
Author-email: rlca@dcc.ufmg.br
Maintainer: Ítalo Cunha
License: GPLv3
Project-URL: Source Code, https://github.com/rlcalmeida/mca
Keywords: network
Platform: UNKNOWN
Classifier: Development Status :: 5 - Production/Stable
Classifier: Environment :: Console
Classifier: Intended Audience :: System Administrators
Classifier: Intended Audience :: Telecommunications Industry
Classifier: License :: OSI Approved :: GNU General Public License v3 (GPLv3)
Classifier: Programming Language :: Python :: 3.6
Classifier: Programming Language :: Python :: 3.7
Classifier: Programming Language :: Python :: 3.8
Classifier: Topic :: System :: Networking
Classifier: Topic :: System :: Networking :: Monitoring
Requires-Python: >=3.6, < 4
Requires-Dist: scapy
